mcap_etl/__init__.py
mcap_etl/main.py
mcap_etl/convert/__init__.py
mcap_etl/convert/executor.py
mcap_etl/convert/mcap.py
mcap_etl/parser/__init__.py
mcap_etl/parser/rosbag.py
mcap_etl/timescale/__init__.py
mcap_etl/timescale/executor.py
mcap_etl/timescale/postgres.py
mcap_etl-0.1.4.dist-info/METADATA
mcap_etl-0.1.4.dist-info/WHEEL
mcap_etl-0.1.4.dist-info/entry_points.txt
mcap_etl-0.1.4.dist-info/top_level.txt
mcap_etl-0.1.4.dist-info/RECORD
