Metadata-Version: 2.1
Name: mcap-etl
Version: 0.1.4
Summary: Transform mcap (or rosbag) files into databases or other files
Home-page: https://github.com/SensorSurf/mcap-etl
Author: SensorSurf
Author-email: support@sensorsurf.com
Project-URL: Bug Reports, https://github.com/SensorSurf/mcap-etl/issues
Project-URL: Source, https://github.com/SensorSurf/mcap-etl
Keywords: ros,ros2,rosbag,mcap,timescale,etl,timeseries,database,etl
Classifier: Development Status :: 3 - Alpha
Classifier: Intended Audience :: Developers
Classifier: License :: OSI Approved :: MIT License
Classifier: Programming Language :: Python :: 3
Classifier: Programming Language :: Python :: 3.6
Classifier: Programming Language :: Python :: 3.7
Classifier: Programming Language :: Python :: 3.8
Classifier: Programming Language :: Python :: 3.9
Requires-Dist: boto3 (==1.26.138)
Requires-Dist: botocore (==1.29.138)
Requires-Dist: jmespath (==1.0.1)
Requires-Dist: lz4 (==4.3.2)
Requires-Dist: mcap (==1.0.2)
Requires-Dist: numpy (==1.23.1)
Requires-Dist: pandas (==2.0.1)
Requires-Dist: psycopg2-binary (==2.9.6)
Requires-Dist: python-dateutil (==2.8.2)
Requires-Dist: pytz (==2023.3)
Requires-Dist: rosbags (==0.9.15)
Requires-Dist: ruamel.yaml (==0.17.26)
Requires-Dist: ruamel.yaml.clib (==0.2.7)
Requires-Dist: s3transfer (==0.6.1)
Requires-Dist: six (==1.16.0)
Requires-Dist: tzdata (==2023.3)
Requires-Dist: urllib3 (==1.26.15)
Requires-Dist: zstandard (==0.21.0)
